Micro_dev-2.1.0.dist-info/DESCRIPTION.rst
Micro_dev-2.1.0.dist-info/METADATA
Micro_dev-2.1.0.dist-info/RECORD
Micro_dev-2.1.0.dist-info/WHEEL
Micro_dev-2.1.0.dist-info/metadata.json
Micro_dev-2.1.0.dist-info/top_level.txt
micro/__init__.py
micro/api/__init__.py
micro/api/endpoints.py
micro/plugin/__init__.py
micro/plugin/pluginbase.py
