Metadata-Version: 2.0
Name: Micro-dev
Version: 2.1.0
Summary: Library to create microservices for Micro
Home-page: https://github.com/humu1us/micro-dev
Author: Felipe Ortiz, Pablo Ahumada
Author-email: fortizc@gmail.com, pablo.ahumadadiaz@gmail.com
License: MIT
Keywords: microservices celery
Platform: UNKNOWN
Classifier: Development Status :: 5 - Production/Stable
Classifier: Intended Audience :: Developers
Classifier: Topic :: Software Development
Classifier: Topic :: System
Classifier: License :: OSI Approved :: MIT License
Classifier: Programming Language :: Python :: 2.7
Classifier: Programming Language :: Python :: 3.5
Classifier: Programming Language :: Python :: 3.6
Requires-Dist: amqp (<=2.2.2,>2)
Requires-Dist: celery (<=4.1.0,>4)
Requires-Dist: kombu (<=4.1.0,>4)
